nanoblocks/__init__.py
nanoblocks/account/__init__.py
nanoblocks/account/account.py
nanoblocks/account/payment/__init__.py
nanoblocks/account/payment/payment.py
nanoblocks/block/__init__.py
nanoblocks/block/block.py
nanoblocks/block/block_factory.py
nanoblocks/block/block_receive.py
nanoblocks/block/block_send.py
nanoblocks/block/block_state.py
nanoblocks/currency/__init__.py
nanoblocks/currency/amount.py
nanoblocks/exceptions/__init__.py
nanoblocks/exceptions/block_not_broadcastable_error.py
nanoblocks/exceptions/insufficient_funds.py
nanoblocks/exceptions/no_pending_block_available_error.py
nanoblocks/exceptions/node_backend_required_error.py
nanoblocks/exceptions/payment_timeout_error.py
nanoblocks/exceptions/work_error.py
nanoblocks/network/__init__.py
nanoblocks/network/nano_network.py
nanoblocks/node/__init__.py
nanoblocks/node/nanonode.py
nanoblocks/protocol/__init__.py
nanoblocks/protocol/crypto/__init__.py
nanoblocks/protocol/crypto/crypto_functions.py
nanoblocks/protocol/crypto/bip39/bip39.txt
nanoblocks/protocol/crypto/ed25519/__init__.py
nanoblocks/protocol/crypto/ed25519/ed25519.py
nanoblocks/protocol/messages/__init__.py
nanoblocks/protocol/messages/account_messages.py
nanoblocks/protocol/messages/network_messages.py
nanoblocks/protocol/messages/node_messages.py
nanoblocks/protocol/messages/work_server_messages.py
nanoblocks/wallet/__init__.py
nanoblocks/wallet/wallet.py
nanoblocks/work/__init__.py
nanoblocks/work/work_server.py
nanoblocks/work/backend/__init__.py
nanoblocks/work/backend/nano_work_server.py
nanoblocks-0.0.5.dist-info/LICENSE
nanoblocks-0.0.5.dist-info/METADATA
nanoblocks-0.0.5.dist-info/WHEEL
nanoblocks-0.0.5.dist-info/top_level.txt
nanoblocks-0.0.5.dist-info/RECORD
