Metadata-Version: 2.1
Name: nanoblocks
Version: 0.0.5
Summary: Another unofficial Python package for managing Nano Cryptocurrency
Home-page: http://github.com/ipazc/nanoblocks
Author: Iván de Paz Centeno
Author-email: ipazc@unileon.es
License: MIT
Keywords: nano protocol cryptocurrency python package wrapper nanoblocks
Platform: UNKNOWN
Classifier: Environment :: Console
Classifier: Intended Audience :: Developers
Classifier: Intended Audience :: Education
Classifier: Intended Audience :: Science/Research
Classifier: Natural Language :: English
Classifier: Programming Language :: Python :: 3.4
Classifier: Programming Language :: Python :: 3.5
Classifier: Programming Language :: Python :: 3.6
Classifier: Programming Language :: Python :: 3.7
Requires-Dist: requests (>=2.18.4)
Requires-Dist: qrcode[pil] (>=6.1)
Requires-Dist: pandas (>=1.1.0)
Requires-Dist: numpy (>=1.18.1)
Requires-Dist: tzlocal (>=2.1)
